llm_extractinator/__init__.py
llm_extractinator/callbacks.py
llm_extractinator/data_loader.py
llm_extractinator/gui.py
llm_extractinator/launch_gui.py
llm_extractinator/launch_schema_builder.py
llm_extractinator/main.py
llm_extractinator/ollama_server.py
llm_extractinator/output_parsers.py
llm_extractinator/prediction_task.py
llm_extractinator/predictor.py
llm_extractinator/prompt_utils.py
llm_extractinator/schema_builder.py
llm_extractinator/translator.py
llm_extractinator/utils.py
llm_extractinator/validator.py
llm_extractinator/prompt_templates/data_extraction/ai_prompt.txt
llm_extractinator/prompt_templates/data_extraction/human_prompt.txt
llm_extractinator/prompt_templates/data_extraction/system_prompt.txt
llm_extractinator/prompt_templates/output_fixing/human_prompt.txt
llm_extractinator/prompt_templates/output_fixing/system_prompt.txt
llm_extractinator/prompt_templates/translation/human_prompt.txt
llm_extractinator/prompt_templates/translation/system_prompt.txt
llm_extractinator-0.5.8.dist-info/licenses/LICENSE
llm_extractinator-0.5.8.dist-info/METADATA
llm_extractinator-0.5.8.dist-info/WHEEL
llm_extractinator-0.5.8.dist-info/entry_points.txt
llm_extractinator-0.5.8.dist-info/top_level.txt
llm_extractinator-0.5.8.dist-info/RECORD
