Metadata-Version: 2.4
Name: llm_extractinator
Version: 0.5.8
Summary: A framework that enables efficient extraction of structured data from unstructured text using large language models (LLMs).
Author: Luc Builtjes
Author-email: Luc.Builtjes@radboudumc.nl
License: Apache License 2.0
Classifier: Programming Language :: Python :: 3
Classifier: License :: OSI Approved :: Apache Software License
Classifier: Operating System :: OS Independent
Requires-Python: >=3.6
License-File: LICENSE
Requires-Dist: pandas>=2.2.3
Requires-Dist: tqdm>=4.67.1
Requires-Dist: pydantic>=2.10.6
Requires-Dist: langchain<1.0.0,>=0.3.16
Requires-Dist: langchain-core>=0.3.32
Requires-Dist: langchain-chroma>=0.2.1
Requires-Dist: langchain-ollama>=0.3.0
Requires-Dist: ollama>=0.5.0
Requires-Dist: tiktoken>=0.8.0
Requires-Dist: streamlit>=1.45.0
Provides-Extra: test
Requires-Dist: pytest>=7.4.0; extra == "test"
Requires-Dist: pytest-cov>=4.1.0; extra == "test"
Dynamic: license-file
